README.rst
setup.cfg
setup.py
tg_profiler/__init__.py
tg_profiler/control.py
tg_profiler.egg-info/PKG-INFO
tg_profiler.egg-info/SOURCES.txt
tg_profiler.egg-info/dependency_links.txt
tg_profiler.egg-info/entry_points.txt
tg_profiler.egg-info/requires.txt
tg_profiler.egg-info/top_level.txt
tg_profiler/adapters/__init__.py
tg_profiler/adapters/tg1.py
tg_profiler/profilers/__init__.py
tg_profiler/profilers/memory_snapshot.py