Metadata-Version: 1.1
Name: tg-profiler
Version: 0.1.5
Summary: A TurboGears 1 extension to profile applications in a lightweight manner, focusing on production profiling
Home-page: https://github.com/sthima/tg-profiler
Author: Matheus Marchini
Author-email: matheus@sthima.com.br
License: MIT
Keywords: profile memory turbogears
Platform: UNKNOWN
Classifier: Development Status :: 3 - Alpha
Classifier: Intended Audience :: Developers
Classifier: Topic :: Software Development :: Debuggers
Classifier: License :: OSI Approved :: MIT License
Classifier: Programming Language :: Python :: 2
Classifier: Programming Language :: Python :: 2.6
Classifier: Programming Language :: Python :: 2.7
